wagtail_model_forms/__init__.py
wagtail_model_forms/blocks.py
wagtail_model_forms/mixins.py
wagtail_model_forms/models.py
wagtail_model_forms/settings.py
wagtail_model_forms/utils.py
wagtail_model_forms/views.py
wagtail_model_forms/wagtail_hooks.py
wagtail_model_forms/contrib/__init__.py
wagtail_model_forms/contrib/crispy_forms.py
wagtail_model_forms/locale/nl/LC_MESSAGES/django.mo
wagtail_model_forms/locale/nl/LC_MESSAGES/django.po
wagtail_model_forms/templates/wagtail_model_forms/form.html
wagtail_model_forms/templates/wagtail_model_forms/form_submissions_report_results.html
wagtail_model_forms/templates/wagtail_model_forms/results_table.html
wagtail_model_forms/templates/wagtail_model_forms/summary.html
wagtail_model_forms/templates/wagtail_model_forms/compat/form_submissions_report.html
wagtail_model_forms-0.8.8.dist-info/licenses/LICENSE
wagtail_model_forms-0.8.8.dist-info/METADATA
wagtail_model_forms-0.8.8.dist-info/WHEEL
wagtail_model_forms-0.8.8.dist-info/top_level.txt
wagtail_model_forms-0.8.8.dist-info/RECORD
